PaqueteDeAlgoritmos/__init__.py
PaqueteDeAlgoritmos/FuncionesPrueba/FuncionesMultivariables.py
PaqueteDeAlgoritmos/FuncionesPrueba/FuncionesUnivariables.py
PaqueteDeAlgoritmos/FuncionesPrueba/__init__.py
PaqueteDeAlgoritmos/MetodosMultivariables/__init__.py
PaqueteDeAlgoritmos/MetodosMultivariables/caminataAleatoria.py
PaqueteDeAlgoritmos/MetodosMultivariables/cauchy.py
PaqueteDeAlgoritmos/MetodosMultivariables/fletcherReeves.py
PaqueteDeAlgoritmos/MetodosMultivariables/hookeJeeves.py
PaqueteDeAlgoritmos/MetodosMultivariables/nelderMeadSimplex.py
PaqueteDeAlgoritmos/MetodosMultivariables/newton.py
PaqueteDeAlgoritmos/MetodosUnivariables/__init__.py
PaqueteDeAlgoritmos/MetodosUnivariables/biseccion.py
PaqueteDeAlgoritmos/MetodosUnivariables/busquedaDorada.py
PaqueteDeAlgoritmos/MetodosUnivariables/fibonacci.py
PaqueteDeAlgoritmos/MetodosUnivariables/intervalHalving.py
PaqueteDeAlgoritmos/MetodosUnivariables/newtonRaphson.py
PaqueteDeAlgoritmos/MetodosUnivariables/secante.py
PaqueteDeAlgoritmos-0.1.dist-info/METADATA
PaqueteDeAlgoritmos-0.1.dist-info/WHEEL
PaqueteDeAlgoritmos-0.1.dist-info/top_level.txt
PaqueteDeAlgoritmos-0.1.dist-info/RECORD
